{"showCaptionBar":false,"showDataInfoBar":false,"xDataControlName":"form","getPSDEViewCodeName":"MainView9_Related","caption":"需求","title":"需求编辑视图","accUserMode":2,"enableDP":true,"getPSAppViewNavParams":[{"rawValue":false,"value":"frombug","key":"frombug","name":"frombug"}],"getPSViewLayoutPanel":{"layoutPanel":true,"useDefaultLayout":true,"controlType":"VIEWLAYOUTPANEL","codeName":"Layoutpanel","controlStyle":"APPDEEDITVIEW9_STYLE2","getPSAppDataEntity":{"modelref":true,"path":"PSSYSAPPS/Web/PSAPPDATAENTITIES/Story.json"},"name":"layoutpanel","getPSControlParam":{}},"getPSAppViewEngines":[{"engineType":"EditView9","engineCat":"VIEW","getPSUIEngineParams":[{"name":"FORM","paramType":"CTRL"},{"name":"P2K","value":0,"paramType":"VALUE"}],"name":"engine"}],"getPSAppViewNavContexts":[{"rawValue":false,"value":"frombug","key":"FROMBUG","name":"FROMBUG"}],"getPSControls":[{"infoFormMode":true,"showFormNavBar":false,"enableAutoSave":false,"getCreatePSControlAction":{"modelref":true,"id":"create"},"getUpdatePSControlAction":{"modelref":true,"id":"update"},"getRemovePSControlAction":{"modelref":true,"id":"remove"},"getGetPSControlAction":{"modelref":true,"id":"load"},"getGetDraftPSControlAction":{"modelref":true,"id":"loaddraft"},"getGetDraftFromPSControlAction":{"modelref":true,"id":"loaddraftfrom"},"controlType":"FORM","readOnly":false,"getPSLayout":{"layout":"TABLE_24COL","columnCount":24},"getPSDEFormPages":[{"getPSDEFormDetails":[{"actionGroupExtractMode":"ITEM","infoGroupMode":true,"getPSLayout":{"layout":"TABLE_24COL","columnCount":24},"getPSDEFormDetails":[{"needSave":false,"refreshItemsSetParamOnly":false,"parentDataJO":{"srfparentdefname":"STORY","srfparentdename":"ZT_STORY","SRFPARENTTYPE":"DER1N","srfparentmode":"DER1N_ZT_TASK_ZT_STORY_STORY","SRFDER1NID":"DER1N_ZT_TASK_ZT_STORY_STORY"},"getPSAppView":{"rowEditDefault":false,"enableExport":true,"enableImport":true,"enableRowEdit":false,"gridRowActiveMode":2,"enableFilter":false,"xDataControlName":"grid","showCaptionBar":false,"getPSDEViewCodeName":"GridView9_StoryRelated","caption":"相关任务","title":"任务表格视图","accUserMode":2,"enableDP":true,"getPSAppViewNavParams":[{"rawValue":false,"value":"srfparentkey","key":"n_story_eq","name":"n_story_eq"}],"getPSViewLayoutPanel":{"layoutPanel":true,"useDefaultLayout":true,"controlType":"VIEWLAYOUTPANEL","codeName":"Layoutpanel","controlStyle":"APPDEGRIDVIEW9_STYLE2","getPSAppDataEntity":{"modelref":true,"path":"PSSYSAPPS/Web/PSAPPDATAENTITIES/Task.json"},"name":"layoutpanel","getPSControlParam":{}},"getPSAppViewEngines":[{"engineType":"GridView9","engineCat":"VIEW","getPSUIEngineParams":[{"name":"OPENDATA","paramType":"LOGIC"},{"name":"NEWDATA","paramType":"LOGIC"},{"name":"GRID","paramType":"CTRL"}],"name":"engine"}],"getPSAppViewNavContexts":[{"rawValue":false,"value":"srfparentkey","key":"N_STORY_EQ","name":"N_STORY_EQ"}],"getPSControls":[{"getPSDEGridDataItems":[{"getPSAppDEField":{"name":"ID","codeName":"Id"},"name":"id","dataType":1},{"getPSAppDEField":{"name":"STORY","codeName":"Story"},"name":"story","dataType":1},{"getPSAppDEField":{"name":"PROJECT","codeName":"Project"},"name":"project","dataType":1},{"getPSAppDEField":{"name":"MODULE","codeName":"Module"},"name":"module","dataType":1},{"getPSAppDEField":{"name":"FROMBUG","codeName":"FromBug"},"name":"frombug","dataType":1},{"getPSAppDEField":{"name":"PLAN","codeName":"Plan"},"name":"plan","dataType":1},{"getPSAppDEField":{"name":"NAME","codeName":"Name"},"name":"name","dataType":25},{"getPSAppDEField":{"name":"PARENT","codeName":"Parent"},"name":"parent","dataType":1},{"getPSAppDEField":{"name":"PROJECTNAME","codeName":"ProjectName"},"name":"projectname","dataType":25},{"name":"srfmstag","dataType":25},{"getPSAppDEField":{"name":"NAME","codeName":"Name"},"name":"srfmajortext","dataType":25},{"dataAccessAction":true,"getPSAppDEField":{"name":"ID","codeName":"Id"},"name":"srfdataaccaction","dataType":1},{"getPSAppDEField":{"name":"ID","codeName":"Id"},"name":"srfkey","dataType":1}],"singleSelect":true,"enableColFilter":false,"enableRowNew":false,"enableRowEditOrder":false,"noSort":false,"getPSDEGridEditItems":[{"getPSEditor":{"editorType":"HIDDEN","name":"srfkey"},"getPSAppDEField":{"name":"ID","codeName":"Id"},"allowEmpty":true,"enableCond":0,"ignoreInput":0,"codeName":"srfkey","caption":"编号","name":"srfkey"}],"hasWFDataItems":false,"getRemovePSControlAction":{"getPSAppDEMethod":{"modelref":true,"id":"Remove"},"getPSAppDataEntity":{"modelref":true,"path":"PSSYSAPPS/Web/PSAPPDATAENTITIES/Task.json"},"dataAccessAction":"DELETE","actionName":"Remove","actionType":"DEACTION","name":"remove"},"columnEnableLink":2,"enableRowEdit":false,"controlType":"GRID","enablePagingBar":false,"getMinorSortPSAppDEField":{"name":"ID","codeName":"Id"},"getPSDEGridColumns":[{"excelCaption":"编号","getPSAppDEField":{"name":"ID","codeName":"Id"},"dataItemName":"id","cLConvertMode":"NONE","noPrivDisplayMode":1,"enableSort":true,"width":80,"codeName":"id","caption":"编号","columnType":"DEFGRIDCOLUMN","align":"LEFT","widthUnit":"PX","name":"id"},{"excelCaption":"任务名称","linkValueItem":"srfkey","enableLinkView":true,"getLinkPSAppView":{"modelref":true,"path":"PSSYSAPPS/Web/PSAPPDEVIEWS/TaskMainDashboardView.json"},"getPSAppDEField":{"name":"NAME","codeName":"Name"},"dataItemName":"name","cLConvertMode":"NONE","noPrivDisplayMode":1,"enableSort":true,"width":500,"codeName":"name","caption":"任务名称","columnType":"DEFGRIDCOLUMN","align":"LEFT","widthUnit":"STAR","name":"name"},{"excelCaption":"所属项目","linkValueItem":"project","enableLinkView":true,"getLinkPSAppView":{"modelref":true,"path":"PSSYSAPPS/Web/PSAPPDEVIEWS/ProjectMainTabExpView.json"},"getPSAppDEField":{"name":"PROJECTNAME","codeName":"ProjectName"},"dataItemName":"projectname","cLConvertMode":"NONE","noPrivDisplayMode":1,"enableSort":true,"width":200,"codeName":"projectname","caption":"所属项目","columnType":"DEFGRIDCOLUMN","align":"LEFT","widthUnit":"PX","name":"projectname"}],"codeName":"StoryRelated","minorSortDir":"DESC","enableGroup":false,"hideHeader":true,"forceFit":false,"pagingSize":500,"aggMode":"NONE","groupMode":"NONE","sortMode":"REMOTE","getFetchPSControlAction":{"modelref":true,"id":"fetch"},"hookEventNames":["SELECTIONCHANGE","BEFORELOAD","ROWDBLCLICK","REMOVE","LOAD"],"getPSAppDataEntity":{"modelref":true,"path":"PSSYSAPPS/Web/PSAPPDATAENTITIES/Task.json"},"dynaModelFilePath":"PSSYSAPPS/Web/PSAPPDATAENTITIES/Task/PSGRIDS/StoryRelated.json","logicName":"嵌入需求任务表格（无分页）","name":"grid","getPSControlParam":{"autoLoad":true,"showBusyIndicator":true,"id":"GRID"},"modelid":"a6062eb5b7d59e89217bfd05118fcf3a","getPSControlHandler":{"userDRAction":"READ","getPSHandlerActions":[{"getPSAppDEMethod":{"modelref":true,"id":"Update"},"getPSAppDataEntity":{"modelref":true,"path":"PSSYSAPPS/Web/PSAPPDATAENTITIES/Task.json"},"dataAccessAction":"UPDATE","actionName":"Update","actionType":"DEACTION","name":"update"},{"getPSAppDEMethod":{"modelref":true,"id":"FetchDefault"},"getPSAppDataEntity":{"modelref":true,"path":"PSSYSAPPS/Web/PSAPPDATAENTITIES/Task.json"},"actionType":"DEDATASET","name":"fetch"},{"getPSAppDEMethod":{"modelref":true,"id":"Remove"},"getPSAppDataEntity":{"modelref":true,"path":"PSSYSAPPS/Web/PSAPPDATAENTITIES/Task.json"},"dataAccessAction":"DELETE","actionName":"Remove","actionType":"DEACTION","name":"remove"},{"getPSAppDEMethod":{"modelref":true,"id":"Get"},"getPSAppDataEntity":{"modelref":true,"path":"PSSYSAPPS/Web/PSAPPDATAENTITIES/Task.json"},"dataAccessAction":"READ","actionName":"Get","actionType":"DEACTION","name":"load"},{"getPSAppDEMethod":{"modelref":true,"id":"GetDraft"},"getPSAppDataEntity":{"modelref":true,"path":"PSSYSAPPS/Web/PSAPPDATAENTITIES/Task.json"},"dataAccessAction":"CREATE","actionName":"GetDraft","actionType":"DEACTION","name":"loaddraft"},{"getPSAppDEMethod":{"modelref":true,"id":"Create"},"getPSAppDataEntity":{"modelref":true,"path":"PSSYSAPPS/Web/PSAPPDATAENTITIES/Task.json"},"dataAccessAction":"CREATE","actionName":"Create","actionType":"DEACTION","name":"create"}],"enableDEFieldPrivilege":false,"id":"数据表格处理器"}}],"viewStyle":"STYLE2","getPSAppDataEntity":{"modelref":true,"path":"PSSYSAPPS/Web/PSAPPDATAENTITIES/Task.json"},"getPSAppViewLogics":[{"logicTrigger":"CUSTOM","getPSAppUILogic":{"enableBatchAdd":false,"batchAddOnly":false,"enableWizardAdd":false,"actionAfterWizard":"DEFAULT","viewLogicType":"APP_NEWDATA","logicType":"PREDEFINED","name":"新建数据"},"logicType":"SYSUILOGIC","name":"newdata"},{"logicTrigger":"CUSTOM","getPSAppUILogic":{"getOpenDataPSAppView":{"getRefPSAppView":{"modelref":true,"path":"PSSYSAPPS/Web/PSAPPDEVIEWS/TaskMainDashboardView.json"}},"viewLogicType":"APP_OPENDATA","getPSAppUILogicRefViews":[{"getRefPSAppView":{"modelref":true,"path":"PSSYSAPPS/Web/PSAPPDEVIEWS/TaskMainDashboardView.json"}}],"logicType":"PREDEFINED","name":"打开数据"},"logicType":"SYSUILOGIC","name":"opendata"}],"getPSAppViewRefs":[{"getRefPSAppView":{"modelref":true,"path":"PSSYSAPPS/Web/PSAPPDEVIEWS/TaskMainDashboardView.json"},"realTitle":"任务主数据看板视图","realOpenMode":"DRAWER_TOP","name":"EDITDATA"}],"getPSSysImage":{"glyph":"xf0ae@FontAwesome","cssClass":"fa fa-tasks"},"codeName":"TaskGridView9_StoryRelated","viewType":"DEGRIDVIEW9","dynaModelFilePath":"PSSYSAPPS/Web/PSAPPDEVIEWS/TaskGridView9_StoryRelated.json","name":"TaskGridView9_StoryRelated","getPSAppDERSPaths":[[{"getParentPSAppDEField":{"name":"ROOT","codeName":"Root"},"enableCreateDataRS":false,"enableUpdateDataRS":false,"enableGetDataRS":false,"enableSelectDataRS":false,"getMinorPSAppDataEntity":{"modelref":true,"path":"PSSYSAPPS/Web/PSAPPDATAENTITIES/ProjectModule.json"},"getMajorPSAppDataEntity":{"modelref":true,"path":"PSSYSAPPS/Web/PSAPPDATAENTITIES/Project.json"},"enableDEAction":true,"enableSelect":true,"enableDEDataSet":true,"codeName":"ProjectModules","actionRSMode":1,"dataRSMode":0,"rSMode":2,"name":"项目任务模块"},{"getParentPSAppDEField":{"name":"MODULE","codeName":"Module"},"enableCreateDataRS":false,"enableUpdateDataRS":false,"enableGetDataRS":false,"enableSelectDataRS":false,"getMinorPSAppDataEntity":{"modelref":true,"path":"PSSYSAPPS/Web/PSAPPDATAENTITIES/Task.json"},"getMajorPSAppDataEntity":{"modelref":true,"path":"PSSYSAPPS/Web/PSAPPDATAENTITIES/ProjectModule.json"},"enableDEAction":true,"enableSelect":true,"enableDEDataSet":true,"codeName":"Tasks","actionRSMode":1,"dataRSMode":0,"rSMode":2,"name":"任务模块"}],[{"getParentPSAppDEField":{"name":"PRODUCT","codeName":"Product"},"enableCreateDataRS":false,"enableUpdateDataRS":false,"enableGetDataRS":false,"enableSelectDataRS":false,"getMinorPSAppDataEntity":{"modelref":true,"path":"PSSYSAPPS/Web/PSAPPDATAENTITIES/Story.json"},"getMajorPSAppDataEntity":{"modelref":true,"path":"PSSYSAPPS/Web/PSAPPDATAENTITIES/Product.json"},"enableDEAction":true,"enableSelect":true,"enableDEDataSet":true,"codeName":"Stories","actionRSMode":1,"dataRSMode":0,"rSMode":2,"name":"产品需求"},{"getParentPSAppDEField":{"name":"STORY","codeName":"Story"},"enableCreateDataRS":false,"enableUpdateDataRS":false,"enableGetDataRS":false,"enableSelectDataRS":false,"getMinorPSAppDataEntity":{"modelref":true,"path":"PSSYSAPPS/Web/PSAPPDATAENTITIES/Task.json"},"getMajorPSAppDataEntity":{"modelref":true,"path":"PSSYSAPPS/Web/PSAPPDATAENTITIES/Story.json"},"enableDEAction":true,"enableSelect":true,"enableDEDataSet":true,"codeName":"Tasks","actionRSMode":1,"dataRSMode":0,"rSMode":2,"name":"需求任务"}],[{"getParentPSAppDEField":{"name":"PRODUCT","codeName":"Product"},"enableCreateDataRS":false,"enableUpdateDataRS":false,"enableGetDataRS":false,"enableSelectDataRS":false,"getMinorPSAppDataEntity":{"modelref":true,"path":"PSSYSAPPS/Web/PSAPPDATAENTITIES/ProductPlan.json"},"getMajorPSAppDataEntity":{"modelref":true,"path":"PSSYSAPPS/Web/PSAPPDATAENTITIES/Product.json"},"enableDEAction":true,"enableSelect":true,"enableDEDataSet":true,"codeName":"ProductPlans","actionRSMode":1,"dataRSMode":0,"rSMode":2,"name":"产品计划"},{"getParentPSAppDEField":{"name":"PLAN","codeName":"Plan"},"enableCreateDataRS":false,"enableUpdateDataRS":false,"enableGetDataRS":false,"enableSelectDataRS":false,"getMinorPSAppDataEntity":{"modelref":true,"path":"PSSYSAPPS/Web/PSAPPDATAENTITIES/Task.json"},"getMajorPSAppDataEntity":{"modelref":true,"path":"PSSYSAPPS/Web/PSAPPDATAENTITIES/ProductPlan.json"},"enableDEAction":true,"enableSelect":true,"enableDEDataSet":true,"codeName":"Tasks","actionRSMode":1,"dataRSMode":0,"rSMode":2,"name":"计划任务"}],[{"getParentPSAppDEField":{"name":"PROJECT","codeName":"Project"},"enableCreateDataRS":false,"enableUpdateDataRS":false,"enableGetDataRS":false,"enableSelectDataRS":false,"getMinorPSAppDataEntity":{"modelref":true,"path":"PSSYSAPPS/Web/PSAPPDATAENTITIES/Task.json"},"getMajorPSAppDataEntity":{"modelref":true,"path":"PSSYSAPPS/Web/PSAPPDATAENTITIES/Project.json"},"enableDEAction":true,"enableSelect":true,"enableDEDataSet":true,"codeName":"Tasks","actionRSMode":1,"dataRSMode":0,"rSMode":2,"name":"项目任务"}],[{"getParentPSAppDEField":{"name":"STORY","codeName":"Story"},"enableCreateDataRS":false,"enableUpdateDataRS":false,"enableGetDataRS":false,"enableSelectDataRS":false,"getMinorPSAppDataEntity":{"modelref":true,"path":"PSSYSAPPS/Web/PSAPPDATAENTITIES/Task.json"},"getMajorPSAppDataEntity":{"modelref":true,"path":"PSSYSAPPS/Web/PSAPPDATAENTITIES/Story.json"},"enableDEAction":true,"enableSelect":true,"enableDEDataSet":true,"codeName":"Tasks","actionRSMode":1,"dataRSMode":0,"rSMode":2,"name":"需求任务"}],[{"getParentPSAppDEField":{"name":"PLAN","codeName":"Plan"},"enableCreateDataRS":false,"enableUpdateDataRS":false,"enableGetDataRS":false,"enableSelectDataRS":false,"getMinorPSAppDataEntity":{"modelref":true,"path":"PSSYSAPPS/Web/PSAPPDATAENTITIES/Task.json"},"getMajorPSAppDataEntity":{"modelref":true,"path":"PSSYSAPPS/Web/PSAPPDATAENTITIES/ProductPlan.json"},"enableDEAction":true,"enableSelect":true,"enableDEDataSet":true,"codeName":"Tasks","actionRSMode":1,"dataRSMode":0,"rSMode":2,"name":"计划任务"}],[{"getParentPSAppDEField":{"name":"MODULE","codeName":"Module"},"enableCreateDataRS":false,"enableUpdateDataRS":false,"enableGetDataRS":false,"enableSelectDataRS":false,"getMinorPSAppDataEntity":{"modelref":true,"path":"PSSYSAPPS/Web/PSAPPDATAENTITIES/Task.json"},"getMajorPSAppDataEntity":{"modelref":true,"path":"PSSYSAPPS/Web/PSAPPDATAENTITIES/ProjectModule.json"},"enableDEAction":true,"enableSelect":true,"enableDEDataSet":true,"codeName":"Tasks","actionRSMode":1,"dataRSMode":0,"rSMode":2,"name":"任务模块"}]]},"getPSLayoutPos":{"colMD":24,"layout":"TABLE_24COL"},"codeName":"druipart1","detailType":"DRUIPART","detailStyle":"DEFAULT","showCaption":true,"name":"druipart1"}],"getPSLayoutPos":{"colMD":24,"layout":"TABLE_24COL"},"codeName":"group1","caption":"项目任务","detailType":"GROUPPANEL","detailStyle":"DEFAULT","showCaption":false,"name":"group1"}],"infoGroupMode":true,"getPSLayout":{"layout":"TABLE_24COL","columnCount":24},"codeName":"formpage1","caption":"项目任务","detailType":"FORMPAGE","detailStyle":"DEFAULT","name":"formpage1"},{"getPSDEFormDetails":[{"needSave":false,"refreshItemsSetParamOnly":false,"getPSNavigateParams":[{"rawValue":false,"value":"story","key":"story","name":"story"}],"parentDataJO":{"srfparentdename":"ZT_STORY","SRFPARENTTYPE":"CUSTOM"},"getPSAppView":{"rowEditDefault":false,"enableExport":true,"enableImport":true,"enableRowEdit":false,"gridRowActiveMode":2,"enableFilter":false,"xDataControlName":"grid","showCaptionBar":true,"getPSDEViewCodeName":"GridView9_Related","caption":"相关需求","title":"相关需求","accUserMode":2,"subCaption":"相关需求","enableDP":true,"getPSAppViewNavParams":[{"rawValue":false,"value":"linkStories","key":"linkstories","name":"linkstories"}],"getPSViewLayoutPanel":{"layoutPanel":true,"useDefaultLayout":true,"controlType":"VIEWLAYOUTPANEL","codeName":"Layoutpanel","controlStyle":"APPDEGRIDVIEW9_STYLE2","getPSAppDataEntity":{"modelref":true,"path":"PSSYSAPPS/Web/PSAPPDATAENTITIES/Story.json"},"name":"layoutpanel","getPSControlParam":{}},"getPSAppViewEngines":[{"engineType":"GridView9","engineCat":"VIEW","getPSUIEngineParams":[{"name":"OPENDATA","paramType":"LOGIC"},{"name":"NEWDATA","paramType":"LOGIC"},{"name":"GRID","paramType":"CTRL"}],"name":"engine"}],"getPSControls":[{"getPSDEGridDataItems":[{"getPSAppDEField":{"name":"PRODUCT","codeName":"Product"},"name":"product","dataType":1},{"getPSAppDEField":{"name":"ID","codeName":"Id"},"name":"id","dataType":1},{"getPSAppDEField":{"name":"MODULE","codeName":"Module"},"name":"module","dataType":1},{"getPSAppDEField":{"name":"TITLE","codeName":"Title"},"name":"title","dataType":25},{"getPSAppDEField":{"name":"FROMBUG","codeName":"FromBug"},"name":"frombug","dataType":1},{"getPSAppDEField":{"name":"BRANCH","codeName":"Branch"},"name":"branch","dataType":1},{"getPSAppDEField":{"name":"DUPLICATESTORY","codeName":"DuplicateStory"},"name":"duplicatestory","dataType":1},{"getPSAppDEField":{"name":"PARENT","codeName":"Parent"},"name":"parent","dataType":1},{"name":"srfmstag","dataType":25},{"getPSAppDEField":{"name":"TITLE","codeName":"Title"},"name":"srfmajortext","dataType":25},{"getPSAppDEField":{"name":"TOBUG","codeName":"ToBug"},"name":"tobug","dataType":1},{"dataAccessAction":true,"getPSAppDEField":{"name":"ID","codeName":"Id"},"name":"srfdataaccaction","dataType":1},{"getPSAppDEField":{"name":"ID","codeName":"Id"},"name":"srfkey","dataType":1}],"singleSelect":true,"enableColFilter":false,"enableRowNew":false,"enableRowEditOrder":false,"noSort":false,"getPSDEGridEditItems":[{"getPSEditor":{"editorType":"HIDDEN","name":"srfkey"},"getPSAppDEField":{"name":"ID","codeName":"Id"},"allowEmpty":true,"enableCond":0,"ignoreInput":0,"codeName":"srfkey","caption":"编号","name":"srfkey"}],"hasWFDataItems":false,"getRemovePSControlAction":{"getPSAppDEMethod":{"modelref":true,"id":"Remove"},"getPSAppDataEntity":{"modelref":true,"path":"PSSYSAPPS/Web/PSAPPDATAENTITIES/Story.json"},"dataAccessAction":"DELETE","actionName":"Remove","actionType":"DEACTION","name":"remove"},"columnEnableLink":2,"enableRowEdit":false,"controlType":"GRID","enablePagingBar":false,"getMinorSortPSAppDEField":{"name":"ID","codeName":"Id"},"getPSDEGridColumns":[{"excelCaption":"编号","getPSAppDEField":{"name":"ID","codeName":"Id"},"dataItemName":"id","cLConvertMode":"NONE","noPrivDisplayMode":1,"enableSort":true,"width":70,"codeName":"id","caption":"编号","columnType":"DEFGRIDCOLUMN","align":"LEFT","widthUnit":"PX","name":"id"},{"excelCaption":"需求名称","linkValueItem":"srfkey","enableLinkView":true,"getLinkPSAppView":{"modelref":true,"path":"PSSYSAPPS/Web/PSAPPDEVIEWS/StoryMainView.json"},"getPSAppDEField":{"name":"TITLE","codeName":"Title"},"dataItemName":"title","cLConvertMode":"NONE","noPrivDisplayMode":1,"enableSort":true,"width":500,"codeName":"title","caption":"需求名称","columnType":"DEFGRIDCOLUMN","align":"LEFT","widthUnit":"STAR","name":"title"}],"codeName":"StoryRelated","minorSortDir":"DESC","enableGroup":false,"hideHeader":true,"forceFit":false,"pagingSize":500,"aggMode":"NONE","groupMode":"NONE","sortMode":"REMOTE","getFetchPSControlAction":{"modelref":true,"id":"fetch"},"hookEventNames":["SELECTIONCHANGE","BEFORELOAD","ROWDBLCLICK","REMOVE","LOAD"],"getPSAppDataEntity":{"modelref":true,"path":"PSSYSAPPS/Web/PSAPPDATAENTITIES/Story.json"},"dynaModelFilePath":"PSSYSAPPS/Web/PSAPPDATAENTITIES/Story/PSGRIDS/StoryRelated.json","logicName":"需求相关（无分页）","name":"grid","getPSControlParam":{"autoLoad":true,"showBusyIndicator":true,"id":"GRID"},"modelid":"ef264f07becfeb27e5e5f59d00ce9336","getPSControlHandler":{"userDRAction":"READ","getPSHandlerActions":[{"getPSAppDEMethod":{"modelref":true,"id":"Update"},"getPSAppDataEntity":{"modelref":true,"path":"PSSYSAPPS/Web/PSAPPDATAENTITIES/Story.json"},"dataAccessAction":"UPDATE","actionName":"Update","actionType":"DEACTION","name":"update"},{"getPSAppDEMethod":{"modelref":true,"id":"FetchStoryRelated"},"getPSAppDataEntity":{"modelref":true,"path":"PSSYSAPPS/Web/PSAPPDATAENTITIES/Story.json"},"actionType":"DEDATASET","name":"fetch"},{"getPSAppDEMethod":{"modelref":true,"id":"Remove"},"getPSAppDataEntity":{"modelref":true,"path":"PSSYSAPPS/Web/PSAPPDATAENTITIES/Story.json"},"dataAccessAction":"DELETE","actionName":"Remove","actionType":"DEACTION","name":"remove"},{"getPSAppDEMethod":{"modelref":true,"id":"Get"},"getPSAppDataEntity":{"modelref":true,"path":"PSSYSAPPS/Web/PSAPPDATAENTITIES/Story.json"},"dataAccessAction":"READ","actionName":"Get","actionType":"DEACTION","name":"load"},{"getPSAppDEMethod":{"modelref":true,"id":"GetDraft"},"getPSAppDataEntity":{"modelref":true,"path":"PSSYSAPPS/Web/PSAPPDATAENTITIES/Story.json"},"dataAccessAction":"CREATE","actionName":"GetDraft","actionType":"DEACTION","name":"loaddraft"},{"getPSAppDEMethod":{"modelref":true,"id":"Create"},"getPSAppDataEntity":{"modelref":true,"path":"PSSYSAPPS/Web/PSAPPDATAENTITIES/Story.json"},"dataAccessAction":"CREATE","actionName":"Create","actionType":"DEACTION","name":"create"}],"enableDEFieldPrivilege":false,"id":"数据表格处理器"}}],"viewStyle":"STYLE2","getPSAppDataEntity":{"modelref":true,"path":"PSSYSAPPS/Web/PSAPPDATAENTITIES/Story.json"},"getPSAppViewLogics":[{"logicTrigger":"CUSTOM","getPSAppUILogic":{"enableBatchAdd":false,"batchAddOnly":false,"enableWizardAdd":false,"actionAfterWizard":"DEFAULT","getNewDataPSAppView":{"getRefPSAppView":{"modelref":true,"path":"PSSYSAPPS/Web/PSAPPDEVIEWS/StoryEditView.json"}},"viewLogicType":"APP_NEWDATA","getPSAppUILogicRefViews":[{"getRefPSAppView":{"modelref":true,"path":"PSSYSAPPS/Web/PSAPPDEVIEWS/StoryEditView.json"}}],"logicType":"PREDEFINED","name":"新建数据"},"logicType":"SYSUILOGIC","name":"newdata"},{"logicTrigger":"CUSTOM","getPSAppUILogic":{"getOpenDataPSAppView":{"getRefPSAppView":{"modelref":true,"path":"PSSYSAPPS/Web/PSAPPDEVIEWS/StoryMainView.json"}},"viewLogicType":"APP_OPENDATA","getPSAppUILogicRefViews":[{"getRefPSAppView":{"modelref":true,"path":"PSSYSAPPS/Web/PSAPPDEVIEWS/StoryMainView.json"}}],"logicType":"PREDEFINED","name":"打开数据"},"logicType":"SYSUILOGIC","name":"opendata"}],"getPSAppViewRefs":[{"getRefPSAppView":{"modelref":true,"path":"PSSYSAPPS/Web/PSAPPDEVIEWS/StoryEditView.json"},"realTitle":"需求","realOpenMode":"DRAWER_RIGHT","name":"NEWDATA"},{"getRefPSAppView":{"modelref":true,"path":"PSSYSAPPS/Web/PSAPPDEVIEWS/StoryMainView.json"},"realTitle":"需求数据看板视图","realOpenMode":"DRAWER_TOP","name":"EDITDATA","openMode":"DRAWER_TOP"}],"getPSSysImage":{"glyph":"xf006@FontAwesome","cssClass":"fa fa-star-o"},"codeName":"StoryGridView9_Related","viewType":"DEGRIDVIEW9","dynaModelFilePath":"PSSYSAPPS/Web/PSAPPDEVIEWS/StoryGridView9_Related.json","name":"StoryGridView9_Related","getPSAppDERSPaths":[[{"getParentPSAppDEField":{"name":"PRODUCT","codeName":"Product"},"enableCreateDataRS":false,"enableUpdateDataRS":false,"enableGetDataRS":false,"enableSelectDataRS":false,"getMinorPSAppDataEntity":{"modelref":true,"path":"PSSYSAPPS/Web/PSAPPDATAENTITIES/Story.json"},"getMajorPSAppDataEntity":{"modelref":true,"path":"PSSYSAPPS/Web/PSAPPDATAENTITIES/Product.json"},"enableDEAction":true,"enableSelect":true,"enableDEDataSet":true,"codeName":"Stories","actionRSMode":1,"dataRSMode":0,"rSMode":2,"name":"产品需求"}]]},"getPSLayoutPos":{"colMD":24,"layout":"TABLE_24COL"},"codeName":"druipart4","detailType":"DRUIPART","detailStyle":"DEFAULT","showCaption":true,"name":"druipart4"},{"inputTipClosable":false,"getPSEditor":{"editorType":"HIDDEN","name":"linkstories"},"emptyCaption":false,"noPrivDisplayMode":1,"getPSAppDEField":{"name":"LINKSTORIES","codeName":"LinkStories"},"hidden":true,"allowEmpty":true,"dataType":25,"caption":"相关需求","labelWidth":100,"enableCond":3,"ignoreInput":0,"labelPos":"LEFT","showCaption":true,"getPSLayoutPos":{"colMD":24,"layout":"TABLE_24COL"},"codeName":"linkstories","detailType":"FORMITEM","detailStyle":"DEFAULT","name":"linkstories"},{"needSave":false,"refreshItemsSetParamOnly":false,"parentDataJO":{"srfparentdename":"ZT_STORY","SRFPARENTTYPE":"CUSTOM"},"getPSAppView":{"rowEditDefault":false,"enableExport":true,"enableImport":true,"enableRowEdit":false,"gridRowActiveMode":2,"enableFilter":false,"xDataControlName":"grid","showCaptionBar":true,"getPSDEViewCodeName":"GridView9_Child","caption":"细分需求","title":"细分需求","accUserMode":2,"subCaption":"相关需求","enableDP":true,"getPSAppViewNavParams":[{"rawValue":false,"value":"linkStories","key":"linkstories","name":"linkstories"}],"getPSViewLayoutPanel":{"layoutPanel":true,"useDefaultLayout":true,"controlType":"VIEWLAYOUTPANEL","codeName":"Layoutpanel","controlStyle":"APPDEGRIDVIEW9_STYLE2","getPSAppDataEntity":{"modelref":true,"path":"PSSYSAPPS/Web/PSAPPDATAENTITIES/Story.json"},"name":"layoutpanel","getPSControlParam":{}},"getPSAppViewEngines":[{"engineType":"GridView9","engineCat":"VIEW","getPSUIEngineParams":[{"name":"OPENDATA","paramType":"LOGIC"},{"name":"NEWDATA","paramType":"LOGIC"},{"name":"GRID","paramType":"CTRL"}],"name":"engine"}],"getPSControls":[{"getPSDEGridDataItems":[{"getPSAppDEField":{"name":"PRODUCT","codeName":"Product"},"name":"product","dataType":1},{"getPSAppDEField":{"name":"ID","codeName":"Id"},"name":"id","dataType":1},{"getPSAppDEField":{"name":"MODULE","codeName":"Module"},"name":"module","dataType":1},{"getPSAppDEField":{"name":"TITLE","codeName":"Title"},"name":"title","dataType":25},{"getPSAppDEField":{"name":"FROMBUG","codeName":"FromBug"},"name":"frombug","dataType":1},{"getPSAppDEField":{"name":"BRANCH","codeName":"Branch"},"name":"branch","dataType":1},{"getPSAppDEField":{"name":"DUPLICATESTORY","codeName":"DuplicateStory"},"name":"duplicatestory","dataType":1},{"getPSAppDEField":{"name":"PARENT","codeName":"Parent"},"name":"parent","dataType":1},{"name":"srfmstag","dataType":25},{"getPSAppDEField":{"name":"TITLE","codeName":"Title"},"name":"srfmajortext","dataType":25},{"getPSAppDEField":{"name":"TOBUG","codeName":"ToBug"},"name":"tobug","dataType":1},{"dataAccessAction":true,"getPSAppDEField":{"name":"ID","codeName":"Id"},"name":"srfdataaccaction","dataType":1},{"getPSAppDEField":{"name":"ID","codeName":"Id"},"name":"srfkey","dataType":1}],"singleSelect":true,"enableColFilter":false,"enableRowNew":false,"enableRowEditOrder":false,"noSort":false,"getPSDEGridEditItems":[{"getPSEditor":{"editorType":"HIDDEN","name":"srfkey"},"getPSAppDEField":{"name":"ID","codeName":"Id"},"allowEmpty":true,"enableCond":0,"ignoreInput":0,"codeName":"srfkey","caption":"编号","name":"srfkey"}],"hasWFDataItems":false,"getRemovePSControlAction":{"getPSAppDEMethod":{"modelref":true,"id":"Remove"},"getPSAppDataEntity":{"modelref":true,"path":"PSSYSAPPS/Web/PSAPPDATAENTITIES/Story.json"},"dataAccessAction":"DELETE","actionName":"Remove","actionType":"DEACTION","name":"remove"},"columnEnableLink":2,"enableRowEdit":false,"controlType":"GRID","enablePagingBar":false,"getMinorSortPSAppDEField":{"name":"ID","codeName":"Id"},"getPSDEGridColumns":[{"excelCaption":"编号","getPSAppDEField":{"name":"ID","codeName":"Id"},"dataItemName":"id","cLConvertMode":"NONE","noPrivDisplayMode":1,"enableSort":true,"width":70,"codeName":"id","caption":"编号","columnType":"DEFGRIDCOLUMN","align":"LEFT","widthUnit":"PX","name":"id"},{"excelCaption":"需求名称","linkValueItem":"srfkey","enableLinkView":true,"getLinkPSAppView":{"modelref":true,"path":"PSSYSAPPS/Web/PSAPPDEVIEWS/StoryMainView.json"},"getPSAppDEField":{"name":"TITLE","codeName":"Title"},"dataItemName":"title","cLConvertMode":"NONE","noPrivDisplayMode":1,"enableSort":true,"width":500,"codeName":"title","caption":"需求名称","columnType":"DEFGRIDCOLUMN","align":"LEFT","widthUnit":"STAR","name":"title"}],"codeName":"StoryRelated","minorSortDir":"DESC","enableGroup":false,"hideHeader":true,"forceFit":false,"pagingSize":500,"aggMode":"NONE","groupMode":"NONE","sortMode":"REMOTE","getFetchPSControlAction":{"modelref":true,"id":"fetch"},"hookEventNames":["SELECTIONCHANGE","BEFORELOAD","ROWDBLCLICK","REMOVE","LOAD"],"getPSAppDataEntity":{"modelref":true,"path":"PSSYSAPPS/Web/PSAPPDATAENTITIES/Story.json"},"dynaModelFilePath":"PSSYSAPPS/Web/PSAPPDATAENTITIES/Story/PSGRIDS/StoryRelated.json","logicName":"需求相关（无分页）","name":"grid","getPSControlParam":{"autoLoad":true,"showBusyIndicator":true,"id":"GRID"},"modelid":"ef264f07becfeb27e5e5f59d00ce9336","getPSControlHandler":{"userDRAction":"READ","getPSHandlerActions":[{"getPSAppDEMethod":{"modelref":true,"id":"Update"},"getPSAppDataEntity":{"modelref":true,"path":"PSSYSAPPS/Web/PSAPPDATAENTITIES/Story.json"},"dataAccessAction":"UPDATE","actionName":"Update","actionType":"DEACTION","name":"update"},{"getPSAppDEMethod":{"modelref":true,"id":"FetchStoryChild"},"getPSAppDataEntity":{"modelref":true,"path":"PSSYSAPPS/Web/PSAPPDATAENTITIES/Story.json"},"actionType":"DEDATASET","name":"fetch"},{"getPSAppDEMethod":{"modelref":true,"id":"Remove"},"getPSAppDataEntity":{"modelref":true,"path":"PSSYSAPPS/Web/PSAPPDATAENTITIES/Story.json"},"dataAccessAction":"DELETE","actionName":"Remove","actionType":"DEACTION","name":"remove"},{"getPSAppDEMethod":{"modelref":true,"id":"Get"},"getPSAppDataEntity":{"modelref":true,"path":"PSSYSAPPS/Web/PSAPPDATAENTITIES/Story.json"},"dataAccessAction":"READ","actionName":"Get","actionType":"DEACTION","name":"load"},{"getPSAppDEMethod":{"modelref":true,"id":"GetDraft"},"getPSAppDataEntity":{"modelref":true,"path":"PSSYSAPPS/Web/PSAPPDATAENTITIES/Story.json"},"dataAccessAction":"CREATE","actionName":"GetDraft","actionType":"DEACTION","name":"loaddraft"},{"getPSAppDEMethod":{"modelref":true,"id":"Create"},"getPSAppDataEntity":{"modelref":true,"path":"PSSYSAPPS/Web/PSAPPDATAENTITIES/Story.json"},"dataAccessAction":"CREATE","actionName":"Create","actionType":"DEACTION","name":"create"}],"enableDEFieldPrivilege":false,"id":"数据表格处理器"}}],"viewStyle":"STYLE2","getPSAppDataEntity":{"modelref":true,"path":"PSSYSAPPS/Web/PSAPPDATAENTITIES/Story.json"},"getPSAppViewLogics":[{"logicTrigger":"CUSTOM","getPSAppUILogic":{"enableBatchAdd":false,"batchAddOnly":false,"enableWizardAdd":false,"actionAfterWizard":"DEFAULT","getNewDataPSAppView":{"getRefPSAppView":{"modelref":true,"path":"PSSYSAPPS/Web/PSAPPDEVIEWS/StoryEditView.json"}},"viewLogicType":"APP_NEWDATA","getPSAppUILogicRefViews":[{"getRefPSAppView":{"modelref":true,"path":"PSSYSAPPS/Web/PSAPPDEVIEWS/StoryEditView.json"}}],"logicType":"PREDEFINED","name":"新建数据"},"logicType":"SYSUILOGIC","name":"newdata"},{"logicTrigger":"CUSTOM","getPSAppUILogic":{"getOpenDataPSAppView":{"getRefPSAppView":{"modelref":true,"path":"PSSYSAPPS/Web/PSAPPDEVIEWS/StoryMainView.json"}},"viewLogicType":"APP_OPENDATA","getPSAppUILogicRefViews":[{"getRefPSAppView":{"modelref":true,"path":"PSSYSAPPS/Web/PSAPPDEVIEWS/StoryMainView.json"}}],"logicType":"PREDEFINED","name":"打开数据"},"logicType":"SYSUILOGIC","name":"opendata"}],"getPSAppViewRefs":[{"getRefPSAppView":{"modelref":true,"path":"PSSYSAPPS/Web/PSAPPDEVIEWS/StoryEditView.json"},"realTitle":"需求","realOpenMode":"DRAWER_RIGHT","name":"NEWDATA"},{"getRefPSAppView":{"modelref":true,"path":"PSSYSAPPS/Web/PSAPPDEVIEWS/StoryMainView.json"},"realTitle":"需求数据看板视图","realOpenMode":"DRAWER_TOP","name":"EDITDATA","openMode":"DRAWER_TOP"}],"getPSSysImage":{"glyph":"xf006@FontAwesome","cssClass":"fa fa-star-o"},"codeName":"StoryGridView9_Child","viewType":"DEGRIDVIEW9","dynaModelFilePath":"PSSYSAPPS/Web/PSAPPDEVIEWS/StoryGridView9_Child.json","name":"StoryGridView9_Child","getPSAppDERSPaths":[[{"getParentPSAppDEField":{"name":"PRODUCT","codeName":"Product"},"enableCreateDataRS":false,"enableUpdateDataRS":false,"enableGetDataRS":false,"enableSelectDataRS":false,"getMinorPSAppDataEntity":{"modelref":true,"path":"PSSYSAPPS/Web/PSAPPDATAENTITIES/Story.json"},"getMajorPSAppDataEntity":{"modelref":true,"path":"PSSYSAPPS/Web/PSAPPDATAENTITIES/Product.json"},"enableDEAction":true,"enableSelect":true,"enableDEDataSet":true,"codeName":"Stories","actionRSMode":1,"dataRSMode":0,"rSMode":2,"name":"产品需求"}]]},"getPSLayoutPos":{"colMD":24,"layout":"TABLE_24COL"},"codeName":"druipart5","detailType":"DRUIPART","detailStyle":"DEFAULT","showCaption":true,"name":"druipart5"},{"inputTipClosable":false,"getPSEditor":{"editorType":"HIDDEN","name":"frombug"},"emptyCaption":false,"noPrivDisplayMode":1,"getPSAppDEField":{"name":"FROMBUG","codeName":"FromBug"},"hidden":true,"allowEmpty":true,"dataType":1,"caption":"来源Bug","labelWidth":100,"enableCond":3,"ignoreInput":0,"labelPos":"LEFT","showCaption":true,"getPSLayoutPos":{"colMD":24,"layout":"TABLE_24COL"},"codeName":"frombug","detailType":"FORMITEM","detailStyle":"DEFAULT","name":"frombug"},{"inputTipClosable":false,"getPSEditor":{"editorType":"HIDDEN","name":"childstories"},"emptyCaption":false,"noPrivDisplayMode":1,"getPSAppDEField":{"name":"CHILDSTORIES","codeName":"ChildStories"},"hidden":true,"allowEmpty":true,"dataType":25,"caption":"细分需求","labelWidth":100,"enableCond":3,"ignoreInput":0,"labelPos":"LEFT","showCaption":true,"getPSLayoutPos":{"colMD":24,"layout":"TABLE_24COL"},"codeName":"childstories","detailType":"FORMITEM","detailStyle":"DEFAULT","name":"childstories"},{"actionGroupExtractMode":"ITEM","infoGroupMode":true,"getPSLayout":{"layout":"TABLE_24COL","columnCount":24},"getPSDEFormDetails":[{"needSave":false,"refreshItems":"frombug","refreshItemsSetParamOnly":false,"getPSNavigateContexts":[{"rawValue":false,"value":"frombug","key":"FROMBUG","name":"FROMBUG"}],"getPSNavigateParams":[{"rawValue":false,"value":"frombug","key":"frombug","name":"frombug"}],"parentDataJO":{"srfparentdename":"ZT_STORY","SRFPARENTTYPE":"CUSTOM"},"getPSAppView":{"rowEditDefault":false,"enableExport":true,"enableImport":true,"enableRowEdit":false,"gridRowActiveMode":2,"enableFilter":false,"xDataControlName":"grid","showCaptionBar":true,"getPSDEViewCodeName":"GridView9_StoryFormBug","caption":"来源Bug","title":"来源Bug","accUserMode":2,"enableDP":true,"getPSAppViewNavParams":[{"rawValue":true,"value":"null","key":"story","name":"story"},{"rawValue":false,"value":"frombug","key":"n_id_eq","name":"n_id_eq"}],"getPSViewLayoutPanel":{"layoutPanel":true,"useDefaultLayout":true,"controlType":"VIEWLAYOUTPANEL","codeName":"Layoutpanel","controlStyle":"APPDEGRIDVIEW9_STYLE2","getPSAppDataEntity":{"modelref":true,"path":"PSSYSAPPS/Web/PSAPPDATAENTITIES/Bug.json"},"name":"layoutpanel","getPSControlParam":{}},"getPSAppViewEngines":[{"engineType":"GridView9","engineCat":"VIEW","getPSUIEngineParams":[{"name":"OPENDATA","paramType":"LOGIC"},{"name":"NEWDATA","paramType":"LOGIC"},{"name":"GRID","paramType":"CTRL"}],"name":"engine"}],"getPSAppViewNavContexts":[{"rawValue":true,"value":"null","key":"STORY","name":"STORY"},{"rawValue":false,"value":"frombug","key":"N_ID_EQ","name":"N_ID_EQ"}],"getPSControls":[{"getPSDEGridDataItems":[{"getPSAppDEField":{"name":"TOTASK","codeName":"ToTask"},"name":"totask","dataType":1},{"getPSAppDEField":{"name":"MODULE","codeName":"Module"},"name":"module","dataType":1},{"getPSAppDEField":{"name":"TASK","codeName":"Task"},"name":"task","dataType":1},{"getPSAppDEField":{"name":"TESTTASK","codeName":"Testtask"},"name":"testtask","dataType":1},{"getPSAppDEField":{"name":"TOSTORY","codeName":"ToStory"},"name":"tostory","dataType":1},{"name":"srfmstag","dataType":25},{"getPSAppDEField":{"name":"TITLE","codeName":"Title"},"name":"srfmajortext","dataType":25},{"getPSAppDEField":{"name":"ID","codeName":"Id"},"name":"srfkey","dataType":1},{"dataAccessAction":true,"getPSAppDEField":{"name":"ID","codeName":"Id"},"name":"srfdataaccaction","dataType":1},{"getPSAppDEField":{"name":"DUPLICATEBUG","codeName":"DuplicateBug"},"name":"duplicatebug","dataType":1},{"getPSAppDEField":{"name":"ID","codeName":"Id"},"name":"id","dataType":1},{"getPSAppDEField":{"name":"PRODUCT","codeName":"Product"},"name":"product","dataType":1},{"getPSAppDEField":{"name":"PROJECT","codeName":"Project"},"name":"project","dataType":1},{"getPSAppDEField":{"name":"STORY","codeName":"Story"},"name":"story","dataType":1},{"getPSAppDEField":{"name":"TITLE","codeName":"Title"},"name":"title","dataType":25},{"getPSAppDEField":{"name":"PLAN","codeName":"Plan"},"name":"plan","dataType":1},{"getPSAppDEField":{"name":"REPO","codeName":"Repo"},"name":"repo","dataType":1},{"getPSAppDEField":{"name":"ENTRY","codeName":"Entry"},"name":"entry","dataType":1},{"getPSAppDEField":{"name":"BRANCH","codeName":"Branch"},"name":"branch","dataType":1},{"getPSAppDEField":{"name":"CASE","codeName":"IBizCase"},"name":"case","dataType":1}],"singleSelect":true,"enableColFilter":false,"enableRowNew":false,"enableRowEditOrder":false,"noSort":true,"getPSDEGridEditItems":[{"getPSEditor":{"editorType":"HIDDEN","name":"srfkey"},"getPSAppDEField":{"name":"ID","codeName":"Id"},"allowEmpty":true,"enableCond":0,"ignoreInput":0,"codeName":"srfkey","caption":"Bug编号","name":"srfkey"}],"hasWFDataItems":false,"getRemovePSControlAction":{"getPSAppDEMethod":{"modelref":true,"id":"Remove"},"getPSAppDataEntity":{"modelref":true,"path":"PSSYSAPPS/Web/PSAPPDATAENTITIES/Bug.json"},"dataAccessAction":"DELETE","actionName":"Remove","actionType":"DEACTION","name":"remove"},"columnEnableLink":2,"enableRowEdit":false,"controlType":"GRID","enablePagingBar":true,"getMinorSortPSAppDEField":{"name":"ID","codeName":"Id"},"getPSDEGridColumns":[{"excelCaption":"ID","getPSAppDEField":{"name":"ID","codeName":"Id"},"dataItemName":"id","cLConvertMode":"NONE","noPrivDisplayMode":1,"enableSort":false,"width":70,"codeName":"id","caption":"ID","columnType":"DEFGRIDCOLUMN","align":"LEFT","widthUnit":"PX","name":"id"},{"excelCaption":"Bug标题","linkValueItem":"srfkey","enableLinkView":true,"getLinkPSAppView":{"modelref":true,"path":"PSSYSAPPS/Web/PSAPPDEVIEWS/BugMainDashboardView.json"},"getPSAppDEField":{"name":"TITLE","codeName":"Title"},"dataItemName":"title","cLConvertMode":"NONE","noPrivDisplayMode":1,"enableSort":false,"width":500,"codeName":"title","caption":"Bug标题","columnType":"DEFGRIDCOLUMN","align":"LEFT","widthUnit":"STAR","name":"title"}],"codeName":"StoryRelated","minorSortDir":"DESC","enableGroup":false,"hideHeader":false,"forceFit":false,"pagingSize":10,"aggMode":"NONE","groupMode":"NONE","sortMode":"REMOTE","getFetchPSControlAction":{"modelref":true,"id":"fetch"},"hookEventNames":["SELECTIONCHANGE","BEFORELOAD","ROWDBLCLICK","REMOVE","LOAD"],"getPSAppDataEntity":{"modelref":true,"path":"PSSYSAPPS/Web/PSAPPDATAENTITIES/Bug.json"},"dynaModelFilePath":"PSSYSAPPS/Web/PSAPPDATAENTITIES/Bug/PSGRIDS/StoryRelated.json","logicName":"主表格（需求相关嵌入无分页）","name":"grid","getPSControlParam":{"autoLoad":true,"showBusyIndicator":true,"id":"GRID"},"modelid":"4e05dd1f4e7a7aa93605684fc42296c0","getPSControlHandler":{"userDRAction":"READ","getPSHandlerActions":[{"getPSAppDEMethod":{"modelref":true,"id":"Update"},"getPSAppDataEntity":{"modelref":true,"path":"PSSYSAPPS/Web/PSAPPDATAENTITIES/Bug.json"},"dataAccessAction":"UPDATE","actionName":"Update","actionType":"DEACTION","name":"update"},{"getPSAppDEMethod":{"modelref":true,"id":"FetchDefault"},"getPSAppDataEntity":{"modelref":true,"path":"PSSYSAPPS/Web/PSAPPDATAENTITIES/Bug.json"},"actionType":"DEDATASET","name":"fetch"},{"getPSAppDEMethod":{"modelref":true,"id":"Remove"},"getPSAppDataEntity":{"modelref":true,"path":"PSSYSAPPS/Web/PSAPPDATAENTITIES/Bug.json"},"dataAccessAction":"DELETE","actionName":"Remove","actionType":"DEACTION","name":"remove"},{"getPSAppDEMethod":{"modelref":true,"id":"Get"},"getPSAppDataEntity":{"modelref":true,"path":"PSSYSAPPS/Web/PSAPPDATAENTITIES/Bug.json"},"dataAccessAction":"READ","actionName":"Get","actionType":"DEACTION","name":"load"},{"getPSAppDEMethod":{"modelref":true,"id":"GetDraft"},"getPSAppDataEntity":{"modelref":true,"path":"PSSYSAPPS/Web/PSAPPDATAENTITIES/Bug.json"},"dataAccessAction":"CREATE","actionName":"GetDraft","actionType":"DEACTION","name":"loaddraft"},{"getPSAppDEMethod":{"modelref":true,"id":"Create"},"getPSAppDataEntity":{"modelref":true,"path":"PSSYSAPPS/Web/PSAPPDATAENTITIES/Bug.json"},"dataAccessAction":"CREATE","actionName":"Create","actionType":"DEACTION","name":"create"}],"enableDEFieldPrivilege":false,"id":"数据表格处理器"}}],"viewStyle":"STYLE2","getPSAppDataEntity":{"modelref":true,"path":"PSSYSAPPS/Web/PSAPPDATAENTITIES/Bug.json"},"getPSAppViewLogics":[{"logicTrigger":"CUSTOM","getPSAppUILogic":{"enableBatchAdd":false,"batchAddOnly":false,"enableWizardAdd":false,"actionAfterWizard":"DEFAULT","getNewDataPSAppView":{"getRefPSAppView":{"modelref":true,"path":"PSSYSAPPS/Web/PSAPPDEVIEWS/BugEditView.json"}},"viewLogicType":"APP_NEWDATA","getPSAppUILogicRefViews":[{"getRefPSAppView":{"modelref":true,"path":"PSSYSAPPS/Web/PSAPPDEVIEWS/BugEditView.json"}}],"logicType":"PREDEFINED","name":"新建数据"},"logicType":"SYSUILOGIC","name":"newdata"},{"logicTrigger":"CUSTOM","getPSAppUILogic":{"getOpenDataPSAppView":{"getRefPSAppView":{"modelref":true,"path":"PSSYSAPPS/Web/PSAPPDEVIEWS/BugMainDashboardView.json"}},"viewLogicType":"APP_OPENDATA","getPSAppUILogicRefViews":[{"getRefPSAppView":{"modelref":true,"path":"PSSYSAPPS/Web/PSAPPDEVIEWS/BugMainDashboardView.json"}}],"logicType":"PREDEFINED","name":"打开数据"},"logicType":"SYSUILOGIC","name":"opendata"}],"getPSAppViewRefs":[{"getRefPSAppView":{"modelref":true,"path":"PSSYSAPPS/Web/PSAPPDEVIEWS/BugEditView.json"},"realTitle":"Bug","realOpenMode":"DRAWER_RIGHT","name":"NEWDATA"},{"getRefPSAppView":{"modelref":true,"path":"PSSYSAPPS/Web/PSAPPDEVIEWS/BugMainDashboardView.json"},"realTitle":"Bug数据看板视图","realOpenMode":"DRAWER_TOP","name":"EDITDATA"}],"getPSSysImage":{"glyph":"xf188@FontAwesome","cssClass":"fa fa-bug"},"codeName":"BugGridView9_StoryFormBug","viewType":"DEGRIDVIEW9","dynaModelFilePath":"PSSYSAPPS/Web/PSAPPDEVIEWS/BugGridView9_StoryFormBug.json","name":"BugGridView9_StoryFormBug","getPSAppDERSPaths":[[{"getParentPSAppDEField":{"name":"PRODUCT","codeName":"Product"},"enableCreateDataRS":false,"enableUpdateDataRS":false,"enableGetDataRS":false,"enableSelectDataRS":false,"getMinorPSAppDataEntity":{"modelref":true,"path":"PSSYSAPPS/Web/PSAPPDATAENTITIES/Story.json"},"getMajorPSAppDataEntity":{"modelref":true,"path":"PSSYSAPPS/Web/PSAPPDATAENTITIES/Product.json"},"enableDEAction":true,"enableSelect":true,"enableDEDataSet":true,"codeName":"Stories","actionRSMode":1,"dataRSMode":0,"rSMode":2,"name":"产品需求"},{"getParentPSAppDEField":{"name":"STORY","codeName":"Story"},"enableCreateDataRS":false,"enableUpdateDataRS":false,"enableGetDataRS":false,"enableSelectDataRS":false,"getMinorPSAppDataEntity":{"modelref":true,"path":"PSSYSAPPS/Web/PSAPPDATAENTITIES/Bug.json"},"getMajorPSAppDataEntity":{"modelref":true,"path":"PSSYSAPPS/Web/PSAPPDATAENTITIES/Story.json"},"enableDEAction":true,"enableSelect":true,"enableDEDataSet":true,"codeName":"Bugs","actionRSMode":1,"dataRSMode":0,"rSMode":2,"name":"需求Bug"}],[{"getParentPSAppDEField":{"name":"PROJECT","codeName":"Project"},"enableCreateDataRS":false,"enableUpdateDataRS":false,"enableGetDataRS":false,"enableSelectDataRS":false,"getMinorPSAppDataEntity":{"modelref":true,"path":"PSSYSAPPS/Web/PSAPPDATAENTITIES/Bug.json"},"getMajorPSAppDataEntity":{"modelref":true,"path":"PSSYSAPPS/Web/PSAPPDATAENTITIES/Project.json"},"enableDEAction":true,"enableSelect":true,"enableDEDataSet":true,"codeName":"Bugs","actionRSMode":1,"dataRSMode":0,"rSMode":2,"name":"项目Bug"}],[{"getParentPSAppDEField":{"name":"STORY","codeName":"Story"},"enableCreateDataRS":false,"enableUpdateDataRS":false,"enableGetDataRS":false,"enableSelectDataRS":false,"getMinorPSAppDataEntity":{"modelref":true,"path":"PSSYSAPPS/Web/PSAPPDATAENTITIES/Bug.json"},"getMajorPSAppDataEntity":{"modelref":true,"path":"PSSYSAPPS/Web/PSAPPDATAENTITIES/Story.json"},"enableDEAction":true,"enableSelect":true,"enableDEDataSet":true,"codeName":"Bugs","actionRSMode":1,"dataRSMode":0,"rSMode":2,"name":"需求Bug"}],[{"getParentPSAppDEField":{"name":"PRODUCT","codeName":"Product"},"enableCreateDataRS":false,"enableUpdateDataRS":false,"enableGetDataRS":false,"enableSelectDataRS":false,"getMinorPSAppDataEntity":{"modelref":true,"path":"PSSYSAPPS/Web/PSAPPDATAENTITIES/Bug.json"},"getMajorPSAppDataEntity":{"modelref":true,"path":"PSSYSAPPS/Web/PSAPPDATAENTITIES/Product.json"},"enableDEAction":true,"enableSelect":true,"enableDEDataSet":true,"codeName":"Bugs","actionRSMode":1,"dataRSMode":0,"rSMode":2,"name":"产品BUG"}]]},"getPSLayoutPos":{"colMD":24,"layout":"TABLE_24COL"},"codeName":"druipart6","detailType":"DRUIPART","detailStyle":"DEFAULT","showCaption":true,"name":"druipart6"}],"getPSLayoutPos":{"colMD":24,"layout":"TABLE_24COL"},"codeName":"grouppanel3","caption":"来源Bug","detailType":"GROUPPANEL","detailStyle":"DEFAULT","showCaption":false,"name":"grouppanel3"},{"actionGroupExtractMode":"ITEM","infoGroupMode":true,"getPSLayout":{"layout":"TABLE_24COL","columnCount":24},"getPSDEFormDetails":[{"needSave":false,"refreshItemsSetParamOnly":false,"parentDataJO":{"srfparentdefname":"TOSTORY","srfparentdename":"ZT_STORY","SRFPARENTTYPE":"DER1N","srfparentmode":"DER1N_ZT_BUG_ZT_STORY_TOSTORY","SRFDER1NID":"DER1N_ZT_BUG_ZT_STORY_TOSTORY"},"getPSAppView":{"rowEditDefault":false,"enableExport":true,"enableImport":true,"enableRowEdit":false,"gridRowActiveMode":2,"enableFilter":false,"xDataControlName":"grid","showCaptionBar":true,"getPSDEViewCodeName":"GridView9_StoryRelated","caption":"相关Bug","title":"相关Bug","accUserMode":2,"enableDP":true,"getPSAppViewNavParams":[{"rawValue":false,"value":"srfparentkey","key":"n_story_eq","name":"n_story_eq"}],"getPSViewLayoutPanel":{"layoutPanel":true,"useDefaultLayout":true,"controlType":"VIEWLAYOUTPANEL","codeName":"Layoutpanel","controlStyle":"APPDEGRIDVIEW9_STYLE2","getPSAppDataEntity":{"modelref":true,"path":"PSSYSAPPS/Web/PSAPPDATAENTITIES/Bug.json"},"name":"layoutpanel","getPSControlParam":{}},"getPSAppViewEngines":[{"engineType":"GridView9","engineCat":"VIEW","getPSUIEngineParams":[{"name":"OPENDATA","paramType":"LOGIC"},{"name":"NEWDATA","paramType":"LOGIC"},{"name":"GRID","paramType":"CTRL"}],"name":"engine"}],"getPSAppViewNavContexts":[{"rawValue":false,"value":"srfparentkey","key":"N_STORY_EQ","name":"N_STORY_EQ"}],"getPSControls":[{"getPSDEGridDataItems":[{"getPSAppDEField":{"name":"TOTASK","codeName":"ToTask"},"name":"totask","dataType":1},{"getPSAppDEField":{"name":"MODULE","codeName":"Module"},"name":"module","dataType":1},{"getPSAppDEField":{"name":"TASK","codeName":"Task"},"name":"task","dataType":1},{"getPSAppDEField":{"name":"TESTTASK","codeName":"Testtask"},"name":"testtask","dataType":1},{"getPSAppDEField":{"name":"TOSTORY","codeName":"ToStory"},"name":"tostory","dataType":1},{"name":"srfmstag","dataType":25},{"getPSAppDEField":{"name":"TITLE","codeName":"Title"},"name":"srfmajortext","dataType":25},{"getPSAppDEField":{"name":"ID","codeName":"Id"},"name":"srfkey","dataType":1},{"dataAccessAction":true,"getPSAppDEField":{"name":"ID","codeName":"Id"},"name":"srfdataaccaction","dataType":1},{"getPSAppDEField":{"name":"DUPLICATEBUG","codeName":"DuplicateBug"},"name":"duplicatebug","dataType":1},{"getPSAppDEField":{"name":"ID","codeName":"Id"},"name":"id","dataType":1},{"getPSAppDEField":{"name":"PRODUCT","codeName":"Product"},"name":"product","dataType":1},{"getPSAppDEField":{"name":"PROJECT","codeName":"Project"},"name":"project","dataType":1},{"getPSAppDEField":{"name":"STORY","codeName":"Story"},"name":"story","dataType":1},{"getPSAppDEField":{"name":"TITLE","codeName":"Title"},"name":"title","dataType":25},{"getPSAppDEField":{"name":"PLAN","codeName":"Plan"},"name":"plan","dataType":1},{"getPSAppDEField":{"name":"REPO","codeName":"Repo"},"name":"repo","dataType":1},{"getPSAppDEField":{"name":"ENTRY","codeName":"Entry"},"name":"entry","dataType":1},{"getPSAppDEField":{"name":"BRANCH","codeName":"Branch"},"name":"branch","dataType":1},{"getPSAppDEField":{"name":"CASE","codeName":"IBizCase"},"name":"case","dataType":1}],"singleSelect":true,"enableColFilter":false,"enableRowNew":false,"enableRowEditOrder":false,"noSort":true,"getPSDEGridEditItems":[{"getPSEditor":{"editorType":"HIDDEN","name":"srfkey"},"getPSAppDEField":{"name":"ID","codeName":"Id"},"allowEmpty":true,"enableCond":0,"ignoreInput":0,"codeName":"srfkey","caption":"Bug编号","name":"srfkey"}],"hasWFDataItems":false,"getRemovePSControlAction":{"getPSAppDEMethod":{"modelref":true,"id":"Remove"},"getPSAppDataEntity":{"modelref":true,"path":"PSSYSAPPS/Web/PSAPPDATAENTITIES/Bug.json"},"dataAccessAction":"DELETE","actionName":"Remove","actionType":"DEACTION","name":"remove"},"columnEnableLink":2,"enableRowEdit":false,"controlType":"GRID","enablePagingBar":true,"getMinorSortPSAppDEField":{"name":"ID","codeName":"Id"},"getPSDEGridColumns":[{"excelCaption":"ID","getPSAppDEField":{"name":"ID","codeName":"Id"},"dataItemName":"id","cLConvertMode":"NONE","noPrivDisplayMode":1,"enableSort":false,"width":70,"codeName":"id","caption":"ID","columnType":"DEFGRIDCOLUMN","align":"LEFT","widthUnit":"PX","name":"id"},{"excelCaption":"Bug标题","linkValueItem":"srfkey","enableLinkView":true,"getLinkPSAppView":{"modelref":true,"path":"PSSYSAPPS/Web/PSAPPDEVIEWS/BugMainDashboardView.json"},"getPSAppDEField":{"name":"TITLE","codeName":"Title"},"dataItemName":"title","cLConvertMode":"NONE","noPrivDisplayMode":1,"enableSort":false,"width":500,"codeName":"title","caption":"Bug标题","columnType":"DEFGRIDCOLUMN","align":"LEFT","widthUnit":"STAR","name":"title"}],"codeName":"StoryRelated","minorSortDir":"DESC","enableGroup":false,"hideHeader":false,"forceFit":false,"pagingSize":10,"aggMode":"NONE","groupMode":"NONE","sortMode":"REMOTE","getFetchPSControlAction":{"modelref":true,"id":"fetch"},"hookEventNames":["SELECTIONCHANGE","BEFORELOAD","ROWDBLCLICK","REMOVE","LOAD"],"getPSAppDataEntity":{"modelref":true,"path":"PSSYSAPPS/Web/PSAPPDATAENTITIES/Bug.json"},"dynaModelFilePath":"PSSYSAPPS/Web/PSAPPDATAENTITIES/Bug/PSGRIDS/StoryRelated.json","logicName":"主表格（需求相关嵌入无分页）","name":"grid","getPSControlParam":{"autoLoad":true,"showBusyIndicator":true,"id":"GRID"},"modelid":"4e05dd1f4e7a7aa93605684fc42296c0","getPSControlHandler":{"userDRAction":"READ","getPSHandlerActions":[{"getPSAppDEMethod":{"modelref":true,"id":"Update"},"getPSAppDataEntity":{"modelref":true,"path":"PSSYSAPPS/Web/PSAPPDATAENTITIES/Bug.json"},"dataAccessAction":"UPDATE","actionName":"Update","actionType":"DEACTION","name":"update"},{"getPSAppDEMethod":{"modelref":true,"id":"FetchDefault"},"getPSAppDataEntity":{"modelref":true,"path":"PSSYSAPPS/Web/PSAPPDATAENTITIES/Bug.json"},"actionType":"DEDATASET","name":"fetch"},{"getPSAppDEMethod":{"modelref":true,"id":"Remove"},"getPSAppDataEntity":{"modelref":true,"path":"PSSYSAPPS/Web/PSAPPDATAENTITIES/Bug.json"},"dataAccessAction":"DELETE","actionName":"Remove","actionType":"DEACTION","name":"remove"},{"getPSAppDEMethod":{"modelref":true,"id":"Get"},"getPSAppDataEntity":{"modelref":true,"path":"PSSYSAPPS/Web/PSAPPDATAENTITIES/Bug.json"},"dataAccessAction":"READ","actionName":"Get","actionType":"DEACTION","name":"load"},{"getPSAppDEMethod":{"modelref":true,"id":"GetDraft"},"getPSAppDataEntity":{"modelref":true,"path":"PSSYSAPPS/Web/PSAPPDATAENTITIES/Bug.json"},"dataAccessAction":"CREATE","actionName":"GetDraft","actionType":"DEACTION","name":"loaddraft"},{"getPSAppDEMethod":{"modelref":true,"id":"Create"},"getPSAppDataEntity":{"modelref":true,"path":"PSSYSAPPS/Web/PSAPPDATAENTITIES/Bug.json"},"dataAccessAction":"CREATE","actionName":"Create","actionType":"DEACTION","name":"create"}],"enableDEFieldPrivilege":false,"id":"数据表格处理器"}}],"viewStyle":"STYLE2","getPSAppDataEntity":{"modelref":true,"path":"PSSYSAPPS/Web/PSAPPDATAENTITIES/Bug.json"},"getPSAppViewLogics":[{"logicTrigger":"CUSTOM","getPSAppUILogic":{"enableBatchAdd":false,"batchAddOnly":false,"enableWizardAdd":false,"actionAfterWizard":"DEFAULT","getNewDataPSAppView":{"getRefPSAppView":{"modelref":true,"path":"PSSYSAPPS/Web/PSAPPDEVIEWS/BugEditView.json"}},"viewLogicType":"APP_NEWDATA","getPSAppUILogicRefViews":[{"getRefPSAppView":{"modelref":true,"path":"PSSYSAPPS/Web/PSAPPDEVIEWS/BugEditView.json"}}],"logicType":"PREDEFINED","name":"新建数据"},"logicType":"SYSUILOGIC","name":"newdata"},{"logicTrigger":"CUSTOM","getPSAppUILogic":{"getOpenDataPSAppView":{"getRefPSAppView":{"modelref":true,"path":"PSSYSAPPS/Web/PSAPPDEVIEWS/BugMainDashboardView.json"}},"viewLogicType":"APP_OPENDATA","getPSAppUILogicRefViews":[{"getRefPSAppView":{"modelref":true,"path":"PSSYSAPPS/Web/PSAPPDEVIEWS/BugMainDashboardView.json"}}],"logicType":"PREDEFINED","name":"打开数据"},"logicType":"SYSUILOGIC","name":"opendata"}],"getPSAppViewRefs":[{"getRefPSAppView":{"modelref":true,"path":"PSSYSAPPS/Web/PSAPPDEVIEWS/BugEditView.json"},"realTitle":"Bug","realOpenMode":"DRAWER_RIGHT","name":"NEWDATA"},{"getRefPSAppView":{"modelref":true,"path":"PSSYSAPPS/Web/PSAPPDEVIEWS/BugMainDashboardView.json"},"realTitle":"Bug数据看板视图","realOpenMode":"DRAWER_TOP","name":"EDITDATA"}],"getPSSysImage":{"glyph":"xf188@FontAwesome","cssClass":"fa fa-bug"},"codeName":"BugGridView9_StoryRelated","viewType":"DEGRIDVIEW9","dynaModelFilePath":"PSSYSAPPS/Web/PSAPPDEVIEWS/BugGridView9_StoryRelated.json","name":"BugGridView9_StoryRelated","getPSAppDERSPaths":[[{"getParentPSAppDEField":{"name":"PRODUCT","codeName":"Product"},"enableCreateDataRS":false,"enableUpdateDataRS":false,"enableGetDataRS":false,"enableSelectDataRS":false,"getMinorPSAppDataEntity":{"modelref":true,"path":"PSSYSAPPS/Web/PSAPPDATAENTITIES/Story.json"},"getMajorPSAppDataEntity":{"modelref":true,"path":"PSSYSAPPS/Web/PSAPPDATAENTITIES/Product.json"},"enableDEAction":true,"enableSelect":true,"enableDEDataSet":true,"codeName":"Stories","actionRSMode":1,"dataRSMode":0,"rSMode":2,"name":"产品需求"},{"getParentPSAppDEField":{"name":"STORY","codeName":"Story"},"enableCreateDataRS":false,"enableUpdateDataRS":false,"enableGetDataRS":false,"enableSelectDataRS":false,"getMinorPSAppDataEntity":{"modelref":true,"path":"PSSYSAPPS/Web/PSAPPDATAENTITIES/Bug.json"},"getMajorPSAppDataEntity":{"modelref":true,"path":"PSSYSAPPS/Web/PSAPPDATAENTITIES/Story.json"},"enableDEAction":true,"enableSelect":true,"enableDEDataSet":true,"codeName":"Bugs","actionRSMode":1,"dataRSMode":0,"rSMode":2,"name":"需求Bug"}],[{"getParentPSAppDEField":{"name":"PROJECT","codeName":"Project"},"enableCreateDataRS":false,"enableUpdateDataRS":false,"enableGetDataRS":false,"enableSelectDataRS":false,"getMinorPSAppDataEntity":{"modelref":true,"path":"PSSYSAPPS/Web/PSAPPDATAENTITIES/Bug.json"},"getMajorPSAppDataEntity":{"modelref":true,"path":"PSSYSAPPS/Web/PSAPPDATAENTITIES/Project.json"},"enableDEAction":true,"enableSelect":true,"enableDEDataSet":true,"codeName":"Bugs","actionRSMode":1,"dataRSMode":0,"rSMode":2,"name":"项目Bug"}],[{"getParentPSAppDEField":{"name":"STORY","codeName":"Story"},"enableCreateDataRS":false,"enableUpdateDataRS":false,"enableGetDataRS":false,"enableSelectDataRS":false,"getMinorPSAppDataEntity":{"modelref":true,"path":"PSSYSAPPS/Web/PSAPPDATAENTITIES/Bug.json"},"getMajorPSAppDataEntity":{"modelref":true,"path":"PSSYSAPPS/Web/PSAPPDATAENTITIES/Story.json"},"enableDEAction":true,"enableSelect":true,"enableDEDataSet":true,"codeName":"Bugs","actionRSMode":1,"dataRSMode":0,"rSMode":2,"name":"需求Bug"}],[{"getParentPSAppDEField":{"name":"PRODUCT","codeName":"Product"},"enableCreateDataRS":false,"enableUpdateDataRS":false,"enableGetDataRS":false,"enableSelectDataRS":false,"getMinorPSAppDataEntity":{"modelref":true,"path":"PSSYSAPPS/Web/PSAPPDATAENTITIES/Bug.json"},"getMajorPSAppDataEntity":{"modelref":true,"path":"PSSYSAPPS/Web/PSAPPDATAENTITIES/Product.json"},"enableDEAction":true,"enableSelect":true,"enableDEDataSet":true,"codeName":"Bugs","actionRSMode":1,"dataRSMode":0,"rSMode":2,"name":"产品BUG"}]]},"getPSLayoutPos":{"colMD":24,"layout":"TABLE_24COL"},"codeName":"druipart2","detailType":"DRUIPART","detailStyle":"DEFAULT","showCaption":true,"name":"druipart2"}],"getPSLayoutPos":{"colMD":24,"layout":"TABLE_24COL"},"codeName":"grouppanel1","caption":"相关Bug","detailType":"GROUPPANEL","detailStyle":"DEFAULT","showCaption":false,"name":"grouppanel1"},{"actionGroupExtractMode":"ITEM","infoGroupMode":true,"getPSLayout":{"layout":"TABLE_24COL","columnCount":24},"getPSDEFormDetails":[{"needSave":false,"refreshItemsSetParamOnly":false,"parentDataJO":{"srfparentdefname":"STORY","srfparentdename":"ZT_STORY","SRFPARENTTYPE":"DER1N","srfparentmode":"DER1N_ZT_CASE_ZT_STORY_STORY","SRFDER1NID":"DER1N_ZT_CASE_ZT_STORY_STORY"},"getPSAppView":{"rowEditDefault":false,"enableExport":true,"enableImport":true,"enableRowEdit":false,"gridRowActiveMode":2,"enableFilter":false,"xDataControlName":"grid","showCaptionBar":true,"getPSDEViewCodeName":"GridView9_StoryRelated","caption":"相关用例","title":"相关用例","accUserMode":2,"enableDP":true,"getPSViewLayoutPanel":{"layoutPanel":true,"useDefaultLayout":true,"controlType":"VIEWLAYOUTPANEL","codeName":"Layoutpanel","controlStyle":"APPDEGRIDVIEW9_STYLE2","getPSAppDataEntity":{"modelref":true,"path":"PSSYSAPPS/Web/PSAPPDATAENTITIES/Case.json"},"name":"layoutpanel","getPSControlParam":{}},"getPSAppViewEngines":[{"engineType":"GridView9","engineCat":"VIEW","getPSUIEngineParams":[{"name":"OPENDATA","paramType":"LOGIC"},{"name":"NEWDATA","paramType":"LOGIC"},{"name":"GRID","paramType":"CTRL"}],"name":"engine"}],"getPSControls":[{"getPSDEGridDataItems":[{"getPSAppDEField":{"name":"PRODUCT","codeName":"Product"},"name":"product","dataType":1},{"getPSAppDEField":{"name":"STORY","codeName":"Story"},"name":"story","dataType":1},{"getPSAppDEField":{"name":"MODULE","codeName":"Module"},"name":"module","dataType":1},{"getPSAppDEField":{"name":"TITLE","codeName":"Title"},"name":"title","dataType":25},{"getPSAppDEField":{"name":"PRI","codeName":"Pri"},"name":"pri","dataType":9},{"getPSAppDEField":{"name":"LIB","codeName":"Lib"},"name":"lib","dataType":1},{"getPSAppDEField":{"name":"FROMBUG","codeName":"FromBug"},"name":"frombug","dataType":1},{"getPSAppDEField":{"name":"BRANCH","codeName":"Branch"},"name":"branch","dataType":1},{"getPSAppDEField":{"name":"FROMCASEID","codeName":"FromCaseId"},"name":"fromcaseid","dataType":1},{"name":"srfmstag","dataType":25},{"getPSAppDEField":{"name":"TITLE","codeName":"Title"},"name":"srfmajortext","dataType":25},{"dataAccessAction":true,"getPSAppDEField":{"name":"ID","codeName":"Id"},"name":"srfdataaccaction","dataType":1},{"getPSAppDEField":{"name":"ID","codeName":"Id"},"name":"srfkey","dataType":1}],"singleSelect":true,"enableColFilter":false,"enableRowNew":false,"enableRowEditOrder":false,"noSort":true,"getPSDEGridEditItems":[{"getPSEditor":{"editorType":"HIDDEN","name":"srfkey"},"getPSAppDEField":{"name":"ID","codeName":"Id"},"allowEmpty":true,"enableCond":0,"ignoreInput":0,"codeName":"srfkey","caption":"用例编号","name":"srfkey"}],"hasWFDataItems":false,"getRemovePSControlAction":{"getPSAppDEMethod":{"modelref":true,"id":"Remove"},"getPSAppDataEntity":{"modelref":true,"path":"PSSYSAPPS/Web/PSAPPDATAENTITIES/Case.json"},"dataAccessAction":"DELETE","actionName":"Remove","actionType":"DEACTION","name":"remove"},"columnEnableLink":2,"enableRowEdit":false,"controlType":"GRID","enablePagingBar":true,"getMinorSortPSAppDEField":{"name":"ID","codeName":"Id"},"getPSDEGridColumns":[{"excelCaption":"P","getPSAppDEField":{"name":"PRI","codeName":"Pri"},"dataItemName":"pri","getPSCodeList":{"modelref":true,"path":"PSSYSAPPS/Web/PSAPPCODELISTS/Testcase__pri.json"},"cLConvertMode":"FRONT","noPrivDisplayMode":1,"enableSort":false,"width":70,"codeName":"pri","caption":"P","columnType":"DEFGRIDCOLUMN","align":"LEFT","widthUnit":"PX","name":"pri"},{"excelCaption":"用例标题","linkValueItem":"srfkey","enableLinkView":true,"getLinkPSAppView":{"modelref":true,"path":"PSSYSAPPS/Web/PSAPPDEVIEWS/CaseMainDashboardView.json"},"getPSAppDEField":{"name":"TITLE","codeName":"Title"},"dataItemName":"title","cLConvertMode":"NONE","noPrivDisplayMode":1,"enableSort":false,"width":500,"codeName":"title","caption":"用例标题","columnType":"DEFGRIDCOLUMN","align":"LEFT","widthUnit":"STAR","name":"title"}],"codeName":"StoryRelated","minorSortDir":"DESC","enableGroup":false,"hideHeader":false,"forceFit":false,"pagingSize":10,"aggMode":"NONE","groupMode":"NONE","sortMode":"REMOTE","getFetchPSControlAction":{"modelref":true,"id":"fetch"},"hookEventNames":["SELECTIONCHANGE","BEFORELOAD","ROWDBLCLICK","REMOVE","LOAD"],"getPSAppDataEntity":{"modelref":true,"path":"PSSYSAPPS/Web/PSAPPDATAENTITIES/Case.json"},"dynaModelFilePath":"PSSYSAPPS/Web/PSAPPDATAENTITIES/Case/PSGRIDS/StoryRelated.json","logicName":"主表格（嵌入需求相关无分页）","name":"grid","getPSControlParam":{"autoLoad":true,"showBusyIndicator":true,"id":"GRID"},"modelid":"614575afef20c289cb0161f96021e8b0","getPSControlHandler":{"userDRAction":"READ","getPSHandlerActions":[{"getPSAppDEMethod":{"modelref":true,"id":"Update"},"getPSAppDataEntity":{"modelref":true,"path":"PSSYSAPPS/Web/PSAPPDATAENTITIES/Case.json"},"dataAccessAction":"UPDATE","actionName":"Update","actionType":"DEACTION","name":"update"},{"getPSAppDEMethod":{"modelref":true,"id":"FetchDefault"},"getPSAppDataEntity":{"modelref":true,"path":"PSSYSAPPS/Web/PSAPPDATAENTITIES/Case.json"},"actionType":"DEDATASET","name":"fetch"},{"getPSAppDEMethod":{"modelref":true,"id":"Remove"},"getPSAppDataEntity":{"modelref":true,"path":"PSSYSAPPS/Web/PSAPPDATAENTITIES/Case.json"},"dataAccessAction":"DELETE","actionName":"Remove","actionType":"DEACTION","name":"remove"},{"getPSAppDEMethod":{"modelref":true,"id":"Get"},"getPSAppDataEntity":{"modelref":true,"path":"PSSYSAPPS/Web/PSAPPDATAENTITIES/Case.json"},"dataAccessAction":"READ","actionName":"Get","actionType":"DEACTION","name":"load"},{"getPSAppDEMethod":{"modelref":true,"id":"GetDraft"},"getPSAppDataEntity":{"modelref":true,"path":"PSSYSAPPS/Web/PSAPPDATAENTITIES/Case.json"},"dataAccessAction":"CREATE","actionName":"GetDraft","actionType":"DEACTION","name":"loaddraft"},{"getPSAppDEMethod":{"modelref":true,"id":"Create"},"getPSAppDataEntity":{"modelref":true,"path":"PSSYSAPPS/Web/PSAPPDATAENTITIES/Case.json"},"dataAccessAction":"CREATE","actionName":"Create","actionType":"DEACTION","name":"create"}],"enableDEFieldPrivilege":false,"id":"数据表格处理器"}}],"viewStyle":"STYLE2","getPSAppDataEntity":{"modelref":true,"path":"PSSYSAPPS/Web/PSAPPDATAENTITIES/Case.json"},"getPSAppViewLogics":[{"logicTrigger":"CUSTOM","getPSAppUILogic":{"enableBatchAdd":false,"batchAddOnly":false,"enableWizardAdd":false,"actionAfterWizard":"DEFAULT","getNewDataPSAppView":{"getRefPSAppView":{"modelref":true,"path":"PSSYSAPPS/Web/PSAPPDEVIEWS/CaseEditView.json"}},"viewLogicType":"APP_NEWDATA","getPSAppUILogicRefViews":[{"getRefPSAppView":{"modelref":true,"path":"PSSYSAPPS/Web/PSAPPDEVIEWS/CaseEditView.json"}}],"logicType":"PREDEFINED","name":"新建数据"},"logicType":"SYSUILOGIC","name":"newdata"},{"logicTrigger":"CUSTOM","getPSAppUILogic":{"getOpenDataPSAppView":{"getRefPSAppView":{"modelref":true,"path":"PSSYSAPPS/Web/PSAPPDEVIEWS/CaseMainDashboardView.json"}},"viewLogicType":"APP_OPENDATA","getPSAppUILogicRefViews":[{"getRefPSAppView":{"modelref":true,"path":"PSSYSAPPS/Web/PSAPPDEVIEWS/CaseMainDashboardView.json"}}],"logicType":"PREDEFINED","name":"打开数据"},"logicType":"SYSUILOGIC","name":"opendata"}],"getPSAppViewRefs":[{"getRefPSAppView":{"modelref":true,"path":"PSSYSAPPS/Web/PSAPPDEVIEWS/CaseEditView.json"},"realTitle":"功能测试编辑视图","name":"NEWDATA"},{"getRefPSAppView":{"modelref":true,"path":"PSSYSAPPS/Web/PSAPPDEVIEWS/CaseMainDashboardView.json"},"realTitle":"功能测试","realOpenMode":"DRAWER_TOP","name":"EDITDATA"}],"getPSSysImage":{"glyph":"xf006@FontAwesome","cssClass":"fa fa-star-o"},"codeName":"CaseGridView9_StoryRelated","viewType":"DEGRIDVIEW9","dynaModelFilePath":"PSSYSAPPS/Web/PSAPPDEVIEWS/CaseGridView9_StoryRelated.json","name":"CaseGridView9_StoryRelated","getPSAppDERSPaths":[[{"getParentPSAppDEField":{"name":"PRODUCT","codeName":"Product"},"enableCreateDataRS":false,"enableUpdateDataRS":false,"enableGetDataRS":false,"enableSelectDataRS":false,"getMinorPSAppDataEntity":{"modelref":true,"path":"PSSYSAPPS/Web/PSAPPDATAENTITIES/Story.json"},"getMajorPSAppDataEntity":{"modelref":true,"path":"PSSYSAPPS/Web/PSAPPDATAENTITIES/Product.json"},"enableDEAction":true,"enableSelect":true,"enableDEDataSet":true,"codeName":"Stories","actionRSMode":1,"dataRSMode":0,"rSMode":2,"name":"产品需求"},{"getParentPSAppDEField":{"name":"STORY","codeName":"Story"},"enableCreateDataRS":false,"enableUpdateDataRS":false,"enableGetDataRS":false,"enableSelectDataRS":false,"getMinorPSAppDataEntity":{"modelref":true,"path":"PSSYSAPPS/Web/PSAPPDATAENTITIES/Case.json"},"getMajorPSAppDataEntity":{"modelref":true,"path":"PSSYSAPPS/Web/PSAPPDATAENTITIES/Story.json"},"enableDEAction":true,"enableSelect":true,"enableDEDataSet":true,"codeName":"Cases","actionRSMode":1,"dataRSMode":0,"rSMode":2,"name":"需求用例"}],[{"getParentPSAppDEField":{"name":"STORY","codeName":"Story"},"enableCreateDataRS":false,"enableUpdateDataRS":false,"enableGetDataRS":false,"enableSelectDataRS":false,"getMinorPSAppDataEntity":{"modelref":true,"path":"PSSYSAPPS/Web/PSAPPDATAENTITIES/Case.json"},"getMajorPSAppDataEntity":{"modelref":true,"path":"PSSYSAPPS/Web/PSAPPDATAENTITIES/Story.json"},"enableDEAction":true,"enableSelect":true,"enableDEDataSet":true,"codeName":"Cases","actionRSMode":1,"dataRSMode":0,"rSMode":2,"name":"需求用例"}],[{"getParentPSAppDEField":{"name":"PRODUCT","codeName":"Product"},"enableCreateDataRS":false,"enableUpdateDataRS":false,"enableGetDataRS":false,"enableSelectDataRS":false,"getMinorPSAppDataEntity":{"modelref":true,"path":"PSSYSAPPS/Web/PSAPPDATAENTITIES/Case.json"},"getMajorPSAppDataEntity":{"modelref":true,"path":"PSSYSAPPS/Web/PSAPPDATAENTITIES/Product.json"},"enableDEAction":true,"enableSelect":true,"enableDEDataSet":true,"codeName":"Cases","actionRSMode":1,"dataRSMode":0,"rSMode":2,"name":"产品用例"}]]},"getPSLayoutPos":{"colMD":24,"layout":"TABLE_24COL"},"codeName":"druipart3","detailType":"DRUIPART","detailStyle":"DEFAULT","showCaption":true,"name":"druipart3"}],"getPSLayoutPos":{"colMD":24,"layout":"TABLE_24COL"},"codeName":"grouppanel2","caption":"相关用例","detailType":"GROUPPANEL","detailStyle":"DEFAULT","showCaption":false,"name":"grouppanel2"}],"infoGroupMode":true,"getPSLayout":{"layout":"TABLE_24COL","columnCount":24},"codeName":"formpage2","caption":"相关信息","detailType":"FORMPAGE","detailStyle":"DEFAULT","name":"formpage2"}],"noTabHeader":false,"getPSDEFormItems":[{"modelref":true,"id":"srfupdatedate","hidden":true,"dataType":5,"getPSAppDEField":{"name":"LASTEDITEDDATE","codeName":"LastEditedDate"}},{"modelref":true,"id":"srforikey","hidden":true,"dataType":25},{"modelref":true,"id":"srfkey","hidden":true,"dataType":1,"getPSAppDEField":{"name":"ID","codeName":"Id"}},{"modelref":true,"id":"srfmajortext","hidden":true,"dataType":25,"getPSAppDEField":{"name":"TITLE","codeName":"Title"}},{"modelref":true,"id":"srftempmode","hidden":true,"dataType":25},{"modelref":true,"id":"srfuf","hidden":true,"dataType":25},{"modelref":true,"id":"srfdeid","hidden":true,"dataType":25},{"modelref":true,"id":"srfsourcekey","hidden":true,"dataType":25},{"modelref":true,"id":"linkstories","hidden":true,"dataType":25,"getPSAppDEField":{"name":"LINKSTORIES","codeName":"LinkStories"}},{"modelref":true,"id":"frombug","hidden":true,"dataType":1,"getPSAppDEField":{"name":"FROMBUG","codeName":"FromBug"}},{"modelref":true,"id":"childstories","hidden":true,"dataType":25,"getPSAppDEField":{"name":"CHILDSTORIES","codeName":"ChildStories"}},{"modelref":true,"id":"id","hidden":true,"dataType":1,"getPSAppDEField":{"name":"ID","codeName":"Id"}}],"codeName":"Related","tabHeaderPos":"TOP","hookEventNames":["SAVE","REMOVE","LOAD"],"getPSAppDataEntity":{"modelref":true,"path":"PSSYSAPPS/Web/PSAPPDATAENTITIES/Story.json"},"dynaModelFilePath":"PSSYSAPPS/Web/PSAPPDATAENTITIES/Story/PSFORMS/Related.json","logicName":"关联信息表单","name":"form","getPSControlParam":{"autoLoad":true,"showBusyIndicator":true,"id":"FORM"},"modelid":"8b60e26e59524a9d13c0a408ad494fc0","getPSControlHandler":{"getPSHandlerActions":[{"getPSAppDEMethod":{"modelref":true,"id":"Update"},"getPSAppDataEntity":{"modelref":true,"path":"PSSYSAPPS/Web/PSAPPDATAENTITIES/Story.json"},"dataAccessAction":"UPDATE","actionName":"Update","actionType":"DEACTION","name":"update"},{"getPSAppDataEntity":{"modelref":true,"path":"PSSYSAPPS/Web/PSAPPDATAENTITIES/Story.json"},"dataAccessAction":"CREATE","actionName":"GETDRAFTFROM","actionType":"DEACTION","name":"loaddraftfrom"},{"getPSAppDEMethod":{"modelref":true,"id":"Remove"},"getPSAppDataEntity":{"modelref":true,"path":"PSSYSAPPS/Web/PSAPPDATAENTITIES/Story.json"},"dataAccessAction":"DELETE","actionName":"Remove","actionType":"DEACTION","name":"remove"},{"getPSAppDEMethod":{"modelref":true,"id":"GetDraft"},"getPSAppDataEntity":{"modelref":true,"path":"PSSYSAPPS/Web/PSAPPDATAENTITIES/Story.json"},"dataAccessAction":"CREATE","actionName":"GetDraft","actionType":"DEACTION","name":"loaddraft"},{"getPSAppDEMethod":{"modelref":true,"id":"Get"},"getPSAppDataEntity":{"modelref":true,"path":"PSSYSAPPS/Web/PSAPPDATAENTITIES/Story.json"},"dataAccessAction":"READ","actionName":"Get","actionType":"DEACTION","name":"load"},{"getPSAppDEMethod":{"modelref":true,"id":"Create"},"getPSAppDataEntity":{"modelref":true,"path":"PSSYSAPPS/Web/PSAPPDATAENTITIES/Story.json"},"dataAccessAction":"CREATE","actionName":"Create","actionType":"DEACTION","name":"create"}],"enableDEFieldPrivilege":false,"id":"编辑表单处理器"}}],"viewStyle":"STYLE2","getPSAppDataEntity":{"modelref":true,"path":"PSSYSAPPS/Web/PSAPPDATAENTITIES/Story.json"},"getPSSysImage":{"glyph":"xf006@FontAwesome","cssClass":"fa fa-star-o"},"codeName":"StoryMainView9_Related","viewType":"DEEDITVIEW9","dynaModelFilePath":"PSSYSAPPS/Web/PSAPPDEVIEWS/StoryMainView9_Related.json","name":"StoryMainView9_Related","getPSAppDERSPaths":[[{"getParentPSAppDEField":{"name":"PRODUCT","codeName":"Product"},"enableCreateDataRS":false,"enableUpdateDataRS":false,"enableGetDataRS":false,"enableSelectDataRS":false,"getMinorPSAppDataEntity":{"modelref":true,"path":"PSSYSAPPS/Web/PSAPPDATAENTITIES/Story.json"},"getMajorPSAppDataEntity":{"modelref":true,"path":"PSSYSAPPS/Web/PSAPPDATAENTITIES/Product.json"},"enableDEAction":true,"enableSelect":true,"enableDEDataSet":true,"codeName":"Stories","actionRSMode":1,"dataRSMode":0,"rSMode":2,"name":"产品需求"}]]}